pytokapi/__init__.py
pytokapi-1.0.0.dist-info/METADATA
pytokapi-1.0.0.dist-info/WHEEL
pytokapi-1.0.0.dist-info/top_level.txt
pytokapi-1.0.0.dist-info/RECORD
