Metadata-Version: 2.1
Name: pytokapi
Version: 1.0.0
Summary: TikTok API Video Wrapper
Home-page: UNKNOWN
Author: CryptosByte
Author-email: notcryptos@gmail.com
License: UNKNOWN
Keywords: python,tiktok,api,wrapper
Platform: UNKNOWN
Classifier: Development Status :: 3 - Alpha
Classifier: Intended Audience :: Education
Classifier: Programming Language :: Python :: 2
Classifier: Programming Language :: Python :: 3
Classifier: Operating System :: MacOS :: MacOS X
Classifier: Operating System :: Microsoft :: Windows
Requires-Dist: requests
